{
  "hash": "327138083626f3ce726b4d161a4f3f25",
  "result": {
    "markdown": "---\ntitle: \"आमा\"\ndescription: \"\"\n# author: []\ndate: 2014-04-29\ncategories:\n  - nepali\n  - jhapa\n  - \"2014\"\noutput:\n  distill::distill_article:\n    self_contained: false\ndraft: false\n---\n    \n\n\n\nसन्तानभन्दा अर्को कुनै, संसार, हुन्न आमाको\\\nतिनकै खुशी बाहेक हाँस्ने, आधार, हुन्न आमाको\\\n\n\nजतिसुकै पिरोल्दा नि कृतघ्न भई सन्तानले\\\nतिनको भलो बाहेक कुनै, विचार, हुन्न आमाको\\\n\n\nकाल-अकाल भाँचिइँदा लौराहरु परदेशमा\\\nबुढेसकालका सपना कैले, साकार, हुन्न आमाको\\\n\n\nसन्तानले परिधिमा ब्रह्माण्ड नै समेटे नि\\\nपर्खाइमा चौकोस बाहेक, विहार, हुन्न आमाको\\\n\n\nआमा भन्या मातृभूमि मातृभूमि भन्या आमा\\\nहाम्ले दिने माया बाहेक, आहार, हुन्न आमाको\\\n\n_Republished in April 2021_",
    "supporting": [],
    "filters": [
      "rmarkdown/pagebreak.lua"
    ],
    "includes": [],
    "engineDependencies": {},
    "preserve": {},
    "postProcess": null
  }
}